lib/fastdependency/__init__.py
lib/fastdependency/decorators.py
lib/fastdependency/exceptions.py
lib/fastdependency/resolvables.py
lib/fastdependency/utils.py
fastdependency-0.2.0.dist-info/METADATA
fastdependency-0.2.0.dist-info/WHEEL
fastdependency-0.2.0.dist-info/RECORD
