Metadata-Version: 2.1
Name: fastdependency
Version: 0.2.0
Summary: Dependency Injection Library
Home-page: https://github.com/mahs4d/fastdependency
License: MIT
Author: Mahdi Sadeghi
Author-email: mahdi74sadeghi@gmail.com
Requires-Python: >=3.12,<4.0
Classifier: License :: OSI Approved :: MIT License
Classifier: Programming Language :: Python :: 3
Project-URL: Repository, https://github.com/mahs4d/fastdependency
